powerhouse_helper/Address_Book_Handler.py
powerhouse_helper/Note.py
powerhouse_helper/Note_Book_Handler.py
powerhouse_helper/Snake.py
powerhouse_helper/Sort_Files.py
powerhouse_helper/__init__.py
powerhouse_helper/addressbook.py
powerhouse_helper/addressbook_data.py
powerhouse_helper/main.py
powerhouse_helper/Сalculator.py
python_powerhouse_helper_pretest-1.0.0.dist-info/LICENSE
python_powerhouse_helper_pretest-1.0.0.dist-info/METADATA
python_powerhouse_helper_pretest-1.0.0.dist-info/WHEEL
python_powerhouse_helper_pretest-1.0.0.dist-info/entry_points.txt
python_powerhouse_helper_pretest-1.0.0.dist-info/top_level.txt
python_powerhouse_helper_pretest-1.0.0.dist-info/RECORD
