Metadata-Version: 2.1
Name: python-powerhouse-helper-pretest
Version: 1.0.0
Summary: This is your console assistant by Python Powerhouse
Home-page: https://github.com/NovykovDaniil/python-core-project
Author: Python Powerhouse
License: MIT
Classifier: Programming Language :: Python :: 3
Classifier: License :: OSI Approved :: MIT License
Classifier: Operating System :: OS Independent
License-File: LICENSE
Requires-Dist: prettytable
Requires-Dist: prompt-toolkit
Requires-Dist: pygame
